aco_routing/__init__.py
aco_routing/aco.py
aco_routing/ant.py
aco_routing/graph_api.py
aco_routing/utils.py
aco_routing-1.2.1.dist-info/licenses/LICENSE
tests/__init__.py
tests/test_ant.py
tests/test_graph_api.py
aco_routing-1.2.1.dist-info/METADATA
aco_routing-1.2.1.dist-info/WHEEL
aco_routing-1.2.1.dist-info/top_level.txt
aco_routing-1.2.1.dist-info/RECORD
