Metadata-Version: 2.4
Name: aco_routing
Version: 1.2.1
Summary: A Python package to find the shortest path in a graph using Ant Colony Optimization (ACO)
Home-page: https://github.com/hasnainroopawalla/ant-colony-optimization
Author: Hasnain Roopawalla
Author-email: hasnain.roopawalla@gmail.com
License: MIT
Keywords: python,machinelearning,ai,aco
Classifier: License :: OSI Approved :: MIT License
Classifier: Intended Audience :: Developers
Classifier: Topic :: Scientific/Engineering :: Artificial Intelligence
Classifier: Operating System :: OS Independent
Classifier: Programming Language :: Python :: 3 :: Only
Classifier: Programming Language :: Python :: 3.6
Classifier: Programming Language :: Python :: 3.7
Classifier: Programming Language :: Python :: 3.8
Classifier: Programming Language :: Python :: 3.9
Requires-Python: >=3.6
License-File: LICENSE
Dynamic: author
Dynamic: author-email
Dynamic: classifier
Dynamic: description
Dynamic: description-content-type
Dynamic: home-page
Dynamic: keywords
Dynamic: license
Dynamic: license-file
Dynamic: requires-python
Dynamic: summary
